.DS_Store
fjcommon/__init__.py
fjcommon/__main__.py
fjcommon/args.py
fjcommon/assertions.py
fjcommon/caching.py
fjcommon/config_diff.py
fjcommon/config_parser.py
fjcommon/config_val.py
fjcommon/file_args.py
fjcommon/functools_ext.py
fjcommon/images.py
fjcommon/iterable_ext.py
fjcommon/iterable_tools.py
fjcommon/lifting.py
fjcommon/no_op.py
fjcommon/numpy_ext.py
fjcommon/os_ext.py
fjcommon/printing.py
fjcommon/qparallel.py
fjcommon/qsuba.py
fjcommon/qsuba_git_helper.py
fjcommon/qsubpy.py
fjcommon/run.py
fjcommon/tensorflow.py
fjcommon/test_functools_ext.py
fjcommon/test_iterable_ext.py
fjcommon/test_iterable_tools.py
fjcommon/test_numpy_ext.py
fjcommon/test_tf_helpers.py
fjcommon/test_tf_records.py
fjcommon/tf_helpers.py
fjcommon/tf_records.py
fjcommon/timer.py
fjcommon/unpickle.py
fjcommon-0.2.12.dist-info/LICENSE
fjcommon-0.2.12.dist-info/METADATA
fjcommon-0.2.12.dist-info/WHEEL
fjcommon-0.2.12.dist-info/top_level.txt
fjcommon-0.2.12.dist-info/RECORD
