Metadata-Version: 2.1
Name: fjcommon
Version: 0.2.12
Summary: Python code usable accross projects
Home-page: https://github.com/fab-jul/fjcommon
Author: fab-jul
Author-email: fabianjul@gmail.com
License: UNKNOWN
Platform: UNKNOWN
